<annotation>
	<folder></folder>
	<filename>s7772_jpg.rf.30ef0812f0c2c25bbc5ba2edfa9507c7.jpg</filename>
	<path>s7772_jpg.rf.30ef0812f0c2c25bbc5ba2edfa9507c7.jpg</path>
	<source>
		<database>roboflow.ai</database>
	</source>
	<size>
		<width>750</width>
		<height>500</height>
		<depth>3</depth>
	</size>
	<segmented>0</segmented>
	<object>
		<name>bud</name>
		<pose>Unspecified</pose>
		<truncated>0</truncated>
		<difficult>0</difficult>
		<occluded>0</occluded>
		<bndbox>
			<xmin>260</xmin>
			<xmax>389</xmax>
			<ymin>45</ymin>
			<ymax>292</ymax>
		</bndbox>
	</object>
	<object>
		<name>yellow</name>
		<pose>Unspecified</pose>
		<truncated>0</truncated>
		<difficult>0</difficult>
		<occluded>0</occluded>
		<bndbox>
			<xmin>127</xmin>
			<xmax>244</xmax>
			<ymin>1</ymin>
			<ymax>353</ymax>
		</bndbox>
	</object>
</annotation>
