<annotation>
	<folder></folder>
	<filename>s8578_jpg.rf.b0b733345e0f32e3d53d4c1861c5cc79.jpg</filename>
	<path>s8578_jpg.rf.b0b733345e0f32e3d53d4c1861c5cc79.jpg</path>
	<source>
		<database>roboflow.ai</database>
	</source>
	<size>
		<width>750</width>
		<height>500</height>
		<depth>3</depth>
	</size>
	<segmented>0</segmented>
	<object>
		<name>pod</name>
		<pose>Unspecified</pose>
		<truncated>0</truncated>
		<difficult>0</difficult>
		<occluded>0</occluded>
		<bndbox>
			<xmin>192</xmin>
			<xmax>565</xmax>
			<ymin>366</ymin>
			<ymax>473</ymax>
		</bndbox>
	</object>
	<object>
		<name>bud</name>
		<pose>Unspecified</pose>
		<truncated>0</truncated>
		<difficult>0</difficult>
		<occluded>0</occluded>
		<bndbox>
			<xmin>204</xmin>
			<xmax>350</xmax>
			<ymin>3</ymin>
			<ymax>132</ymax>
		</bndbox>
	</object>
	<object>
		<name>bud</name>
		<pose>Unspecified</pose>
		<truncated>0</truncated>
		<difficult>0</difficult>
		<occluded>0</occluded>
		<bndbox>
			<xmin>79</xmin>
			<xmax>361</xmax>
			<ymin>6</ymin>
			<ymax>180</ymax>
		</bndbox>
	</object>
</annotation>
